{"kind": "wynncraft/ingredient/get/Intermittenstirrups", "code": 200, "timestamp": 1669640574902, "version": "2.1.0", "data": [{"name": "Intermittenstirrups", "tier": 1, "level": 27, "skills": ["WEAPONSMITHING", "WOODWORKING", "TAILORING"], "sprite": {"id": 318, "damage": 0}, "identifications": {"STAMINA": {"minimum": 4, "maximum": 6}, "STAMINA_REGEN": {"minimum": 5, "maximum": 7}}, "itemOnlyIDs": {"durabilityModifier": -34, "strengthRequirement": 0, "dexterityRequirement": 0, "intelligenceRequirement": 0, "defenceRequirement": 0, "agilityRequirement": 3}, "consumableOnlyIDs": {"duration": 0, "charges": 0}, "ingredientPositionModifiers": {"left": 0, "right": 0, "above": 0, "under": 0, "touching": 0, "notTouching": 0}}]}